MANIFEST.in
README.rst
setup.py
docs/CONTRIBUTORS.rst
docs/HISTORY.rst
docs/LICENSE.GPL
docs/LICENSE.txt
seantis/__init__.py
seantis.placemap.egg-info/PKG-INFO
seantis.placemap.egg-info/SOURCES.txt
seantis.placemap.egg-info/dependency_links.txt
seantis.placemap.egg-info/entry_points.txt
seantis.placemap.egg-info/namespace_packages.txt
seantis.placemap.egg-info/not-zip-safe
seantis.placemap.egg-info/requires.txt
seantis.placemap.egg-info/top_level.txt
seantis/placemap/__init__.py
seantis/placemap/configure.zcml
seantis/placemap/interfaces.py
seantis/placemap/profiles.zcml
seantis/placemap/sync.sh
seantis/placemap/testing.py
seantis/placemap/upgrades.zcml
seantis/placemap/utils.py
seantis/placemap/browser/__init__.py
seantis/placemap/browser/base.py
seantis/placemap/browser/configure.zcml
seantis/placemap/browser/map.py
seantis/placemap/browser/source.py
seantis/placemap/browser/sourcelayer.py
seantis/placemap/browser/js/placemap.js
seantis/placemap/browser/templates/map.pt
seantis/placemap/content/__init__.py
seantis/placemap/content/map.py
seantis/placemap/content/source.py
seantis/placemap/locales/seantis.placemap.pot
seantis/placemap/locales/de/LC_MESSAGES/plone.po
seantis/placemap/locales/de/LC_MESSAGES/seantis.placemap.po
seantis/placemap/profiles/default/browserlayer.xml
seantis/placemap/profiles/default/catalog.xml
seantis/placemap/profiles/default/jsregistry.xml
seantis/placemap/profiles/default/metadata.xml
seantis/placemap/profiles/default/seantis.placemap-default.txt
seantis/placemap/profiles/default/types.xml
seantis/placemap/profiles/default/types/seantis.placemap.map.xml
seantis/placemap/profiles/default/types/seantis.placemap.source.xml
seantis/placemap/tests/__init__.py
seantis/placemap/tests/test_kml.py
seantis/placemap/tests/test_map_view.py
seantis/placemap/tests/test_types.py
seantis/placemap/theme/__init__.py
seantis/placemap/theme/configure.zcml
seantis/placemap/theme/theme.scss