Metadata-Version: 1.1
Name: seantis.placemap
Version: 0.2
Summary: Shows placemarks from multiple maps in one map, by combining kml-documents from multiple urls.
Home-page: https://github.com/seantis/seantis.placemap
Author: Seantis GmbH
Author-email: info@seantis.ch
License: GPL v2
Keywords: plone seantis map government municipality kml
Platform: UNKNOWN
Classifier: Framework :: Plone
Classifier: Framework :: Plone :: 4.3
Classifier: Intended Audience :: Developers
Classifier: Topic :: Software Development :: Libraries :: Python Modules
Classifier: Programming Language :: Python
Classifier: Programming Language :: Python :: 2.7
